damv1testhello2025/__init__.py
damv1testhello2025/main.py
damv1testhello2025/send_email.py
damv1testhello2025-0.1.0.dist-info/LICENSE
damv1testhello2025-0.1.0.dist-info/METADATA
damv1testhello2025-0.1.0.dist-info/WHEEL
damv1testhello2025-0.1.0.dist-info/top_level.txt
damv1testhello2025-0.1.0.dist-info/RECORD
