Metadata-Version: 2.1
Name: damv1testhello2025
Version: 0.1.0
Summary: development testhello2025 package
Home-page: UNKNOWN
Author: dhonyabumuhammad (Bekasi)
Author-email: <baba-rtw24133@tutamail.com>
License: UNKNOWN
Keywords: testhello2025,development,testing,email,smtp
Platform: UNKNOWN
Classifier: Development Status :: 4 - Beta
Classifier: Intended Audience :: Developers
Classifier: Operating System :: Unix
Classifier: Operating System :: MacOS :: MacOS X
Classifier: Operating System :: Microsoft :: Windows
Classifier: Programming Language :: Python :: 3
Classifier: Programming Language :: Python :: 3.7
Classifier: Programming Language :: Python :: 3.8
Classifier: Programming Language :: Python :: 3.9
Classifier: Programming Language :: Python :: 3.10
Classifier: Topic :: Software Development :: Debuggers
Classifier: License :: OSI Approved :: MIT License
Requires-Python: >=3.0
License-File: LICENSE
Requires-Dist: python-dotenv==1.0.1
Requires-Dist: requests==2.32.3
